dagster_snowflake_polars/__init__.py
dagster_snowflake_polars/py.typed
dagster_snowflake_polars/snowflake_polars_type_handler.py
dagster_snowflake_polars/version.py
dagster_snowflake_polars-0.28.13.dist-info/licenses/LICENSE
dagster_snowflake_polars-0.28.13.dist-info/METADATA
dagster_snowflake_polars-0.28.13.dist-info/WHEEL
dagster_snowflake_polars-0.28.13.dist-info/top_level.txt
dagster_snowflake_polars-0.28.13.dist-info/RECORD
