Metadata-Version: 2.4
Name: dagster-snowflake-polars
Version: 0.28.13
Summary: Package for integrating Snowflake and Polars with Dagster.
Home-page: https://github.com/dagster-io/dagster/tree/master/python_modules/libraries/dagster-snowflake-polars
Author: Dagster Labs
Author-email: hello@dagsterlabs.com
License: Apache-2.0
Classifier: Programming Language :: Python :: 3.10
Classifier: Programming Language :: Python :: 3.11
Classifier: Programming Language :: Python :: 3.12
Classifier: License :: OSI Approved :: Apache Software License
Classifier: Operating System :: OS Independent
Requires-Python: >=3.10,<3.15
License-File: LICENSE
Requires-Dist: dagster==1.12.13
Requires-Dist: dagster-snowflake==0.28.13
Requires-Dist: polars>=1.0.0
Requires-Dist: requests
Requires-Dist: adbc-driver-snowflake>=1.6.0
Provides-Extra: test
Requires-Dist: certifi==2025.1.31; extra == "test"
Requires-Dist: snowflake-connector-python[pandas]>=3.4.0; extra == "test"
Dynamic: author
Dynamic: author-email
Dynamic: classifier
Dynamic: home-page
Dynamic: license
Dynamic: license-file
Dynamic: provides-extra
Dynamic: requires-dist
Dynamic: requires-python
Dynamic: summary
